
		{
			"TicketType":"OU",
			"Minbet":"3",
			"Maxbet":"500",
			"Payout":null,
			"Bet":"20",
			"QuickBet":"100:10:1",
			"SeqNo":0,
			"Line":1.75,
			"DisplayHDP":"1.75",
			"DisplayOdds":"-0.30",
			"DisplayOddsPair":"0.20",
			"OddsID":205065275,
			"Betteam":"h",
			"LiveScore":true,
			"LiveHomeScore":0,
			"LiveAwayScore":1,
			"BetID":"",
			"ChoiceValue":"Tài",
			"BettypeName":"Tài/Xỉu",
			"HomeName":"Los Angeles FC",
			"AwayName":"Portland Timbers",
			"LeagueName":"US OPEN CUP",
			"Bettype":"3",
			"SportType":1,
			"SportName":"Bóng đá",
			"GameName":"",
			"IsLive":true,
			"IsInPlay":false,
			"Matchid":31148188,
			"MatchCode":null,
			"Code":0,
			"Message":"",
			"isOddsChange":false,
			"AutoAcceptSec":"",
			"MRPercentage":"",
			"OddsInfo":null,
			"PoolType":0,
			"UseBonus":0,
			"DisplayTime":"10:38 PM",
			"HasParlay":false
		}
